microdocs/__init__.py
microdocs/__main__.py
microdocs/builder.py
microdocs/cli.py
microdocs/templates/default.css
microdocs/templates/default.html
microdocs/templates/default.tailwind.css
microdocs/tests/__init__.py
microdocs/tests/test_builder.py
microdocs/tests/test_cli.py
microdocs/tests/test_templates.py
microdocs-1.1.0.dist-info/METADATA
microdocs-1.1.0.dist-info/WHEEL
microdocs-1.1.0.dist-info/entry_points.txt
microdocs-1.1.0.dist-info/licenses/LICENSE
microdocs-1.1.0.dist-info/RECORD
