Metadata-Version: 2.4
Name: microdocs
Version: 1.1.0
Summary: Transform your Markdown files into a self-contained HTML documentation site.
Project-URL: Homepage, https://github.com/bartTC/microdocs/
Project-URL: Repository, https://github.com/bartTC/microdocs/
Project-URL: Documentation, https://github.com/bartTC/microdocs/blob/main/README.md
Project-URL: Changelog, https://github.com/bartTC/microdocs/blob/main/CHANGELOG.md
Project-URL: Bug Tracker, https://github.com/bartTC/microdocs/issues
Author-email: Martin Mahner <martin@mahner.org>
License-Expression: MIT
License-File: LICENSE
Classifier: Development Status :: 5 - Production/Stable
Classifier: Environment :: Console
Classifier: Environment :: Web Environment
Classifier: Intended Audience :: Developers
Classifier: License :: OSI Approved :: MIT License
Classifier: Operating System :: OS Independent
Classifier: Programming Language :: Python
Classifier: Programming Language :: Python :: 3 :: Only
Classifier: Programming Language :: Python :: 3.11
Classifier: Programming Language :: Python :: 3.12
Classifier: Programming Language :: Python :: 3.13
Classifier: Programming Language :: Python :: 3.14
Classifier: Topic :: Documentation
Classifier: Topic :: Internet :: WWW/HTTP
Classifier: Topic :: Software Development :: Documentation
Classifier: Topic :: Software Development :: Libraries :: Python Modules
Classifier: Topic :: Text Processing :: Markup :: HTML
Classifier: Topic :: Text Processing :: Markup :: Markdown
Classifier: Typing :: Typed
Requires-Python: >=3.11
Requires-Dist: jinja2>=3.1.6
Requires-Dist: markdown>=3.10
Requires-Dist: typer>=0.20.0
